lrcfetcher/__init__.py
lrcfetcher/__main__.py
lrcfetcher-0.1.1.dist-info/METADATA
lrcfetcher-0.1.1.dist-info/WHEEL
lrcfetcher-0.1.1.dist-info/entry_points.txt
lrcfetcher-0.1.1.dist-info/RECORD
