Metadata-Version: 2.4
Name: lrcfetcher
Version: 0.1.1
Summary: Fetch lyrics from the internet for you FLAC files
Author-email: Egor Ternovoi <cofob@riseup.net>
Requires-Python: >=3.13
Requires-Dist: mutagen>=1.47.0
Requires-Dist: requests>=2.32.3
Requires-Dist: tqdm>=4.67.1
